{"cameraMode":{"drawMode":0,"name":"Shaded","section":"Shading Mode"},"sceneLighting":true,"audioPlay":false,"sceneViewState":{"m_AlwaysRefresh":false,"showFog":true,"showSkybox":true,"showFlares":true,"showImageEffects":true,"showParticleSystems":true,"showVisualEffectGraphs":true,"m_FxEnabled":true},"in2DMode":false,"pivot":{"x":-2.3952584266662599,"y":1.145071029663086,"z":3.0535616874694826},"rotation":{"x":-0.10444589704275131,"y":0.2951713800430298,"z":-0.03248056024312973,"w":-0.9491637945175171},"size":4.743791103363037,"orthographic":false}